cthulhu/__init__.py
cthulhu/analyses.py
cthulhu/blacklist.py
cthulhu/plot_tools.py
cthulhu/reconstruct.py
cthulhu/rts_log_tools.py
cthulhu/unpack.py
cthulhu-0.2.0.data/scripts/cthulhu_format_convertor.py
cthulhu-0.2.0.data/scripts/cthulhu_rts2format.py
cthulhu-0.2.0.data/scripts/cthulhu_wrapper.py
cthulhu-0.2.0.dist-info/LICENSE
cthulhu-0.2.0.dist-info/METADATA
cthulhu-0.2.0.dist-info/WHEEL
cthulhu-0.2.0.dist-info/top_level.txt
cthulhu-0.2.0.dist-info/RECORD
