Metadata-Version: 2.1
Name: cthulhu
Version: 0.2.0
Summary: Python software suite for various ionospheric analyses
Home-page: https://gitlab.com/chjordan/cthulhu
Author: Christopher Jordan
Author-email: christopherjordan87@gmail.com
License: MPL 2.0
Keywords: signal processing
Platform: UNKNOWN
Requires-Dist: numpy
Requires-Dist: scipy
Requires-Dist: astropy
Requires-Dist: matplotlib
Requires-Dist: pyGrad2Surf
Requires-Dist: pyyaml
Requires-Dist: future
